01_blink/blink.sv

// =====================================================================
// blink.sv -- LED blink module for the Arty A7-100T
//
// Uses the board's 100 MHz clock to periodically toggle LED0.
// HALF_PERIOD determines how many clock cycles occur between each
// LED state change. With the default value of 50,000,000, the LED
// toggles every 0.5 seconds, producing a 1 Hz blink rate.
//
// The active-low reset input clears the counter and turns LED0 off.
// HALF_PERIOD is a parameter so it can be overridden with a smaller
// value in the testbench for faster simulation.
// =====================================================================

`timescale 1ns / 1ps

// Blinks LED0 using the Arty A7-100T's 100 MHz clock.
// The LED changes state after every HALF_PERIOD clock cycles.

module blink #(
    // Number of clock cycles before the LED changes state.
    // 50,000,000 cycles at 100 MHz = 0.5 seconds.
    parameter int HALF_PERIOD = 50_000_000
) (
    input  logic clk,       // 100 MHz onboard clock
    input  logic rst_n,     // Active-low reset button
    output logic led0       // LED0 output
);

    // Counter used to measure the required number of clock cycles.
    logic [$clog2(HALF_PERIOD)-1:0] counter;

    // Counter and LED are updated on every rising edge of the clock.
    always_ff @(posedge clk) begin

        // Reset the counter and turn the LED off.
        if (!rst_n) begin
            counter <= '0;
            led0    <= 1'b0;

        // When the counter reaches HALF_PERIOD,
        // reset the counter and change the LED state.
        end else if (counter == HALF_PERIOD - 1) begin
            counter <= '0;
            led0    <= ~led0;

        // Otherwise, continue counting clock cycles.
        end else begin
            counter <= counter + 1'b1;
        end

    end

endmodule

01_blink/blink_tb.sv

// =====================================================================
// blink_tb.sv -- testbench for blink.sv
//
// We override HALF_PERIOD down to a small number for simulation speed
// (blink.sv's real value of 50,000,000 would take far too long to
// simulate) -- no manual edit-and-revert of blink.sv needed, since
// HALF_PERIOD is a parameter this testbench overrides at instantiation.
//
// Stimulus is driven on the NEGEDGE of clk to avoid a same-timestep race
// with the DUT's own always_ff @(posedge clk) block.
// =====================================================================

`timescale 1ns / 1ps

module blink_tb;

    // Use a small value so the LED toggles quickly during simulation.
    localparam int SIM_HALF_PERIOD = 10;

    logic clk = 0;
    logic rst_n;
    logic led0;

    // Instantiate the blink module with the smaller simulation value.
    blink #(
        .HALF_PERIOD(SIM_HALF_PERIOD)
    ) dut (
        .clk,
        .rst_n,
        .led0
    );

    // 10 ns clock period = 100 MHz.
    always #5 clk = ~clk;

    int toggle_count;
    logic led0_prev;

    initial begin
        // Create waveform file for viewing in GTKWave/Vivado.
        $dumpfile("blink.vcd");
        $dumpvars(0, blink_tb);

        toggle_count = 0;
        rst_n = 0;

        $display("==============================================");
        $display("        BLINK MODULE SIMULATION START         ");
        $display("==============================================");
        $display("Clock period       : 10 ns");
        $display("Clock frequency    : 100 MHz");
        $display("HALF_PERIOD        : %0d clocks", SIM_HALF_PERIOD);
        $display("----------------------------------------------");

        // Hold reset active for a few clock cycles.
        $display("[%0t ns] Applying reset...", $time);

        @(negedge clk);
        @(negedge clk);
        @(negedge clk);

        // Release reset.
        rst_n = 1;
        led0_prev = led0;

        $display("[%0t ns] Reset released.", $time);
        $display("[%0t ns] LED0 initial state = %b", $time, led0);
        $display("----------------------------------------------");

        // Run long enough to observe several LED toggles.
        repeat (SIM_HALF_PERIOD * 8) begin
            @(posedge clk);

            // Detect every change in LED0.
            if (led0 !== led0_prev) begin
                toggle_count++;
                led0_prev = led0;

                $display(
                    "[%0t ns] LED0 toggled -> %b  |  Toggle #%0d",
                    $time,
                    led0,
                    toggle_count
                );
            end
        end

        $display("----------------------------------------------");
        $display("Simulation finished.");
        $display("Total clock cycles checked : %0d",
                 SIM_HALF_PERIOD * 8);
        $display("Total LED0 toggles         : %0d",
                 toggle_count);
        $display("Expected toggles           : approximately 8");

        // Check whether the LED toggled approximately the expected
        // number of times.
        if (toggle_count >= 6 && toggle_count <= 10) begin
            $display("RESULT: PASS");
            $display("LED0 is toggling at approximately the expected rate.");
        end
        else begin
            $display("RESULT: FAIL");
            $display("LED0 toggle count is outside the expected range.");
            $display("Check the counter and reset logic.");
        end

        $display("----------------------------------------------");
        $display("Note: HALF_PERIOD = %0d is used only for simulation.",
                 SIM_HALF_PERIOD);
        $display("Hardware uses the default HALF_PERIOD = 50,000,000.");
        $display("==============================================");

        $finish;
    end

endmodule

01_blink/blink.vcd
$date
	Fri Oct  2 14:23:30 2026
$end
$version
	QuestaSim Version 2024.1
$end
$timescale
	1ps
$end

$scope module blink_tb $end
$var parameter 32 ! SIM_HALF_PERIOD $end
$var reg 1 " clk $end
$var reg 1 # rst_n $end
$var reg 1 $ led0 $end
$var integer 32 % toggle_count $end
$var reg 1 & led0_prev $end

$scope module dut $end
$var parameter 32 ' HALF_PERIOD $end
$var wire 1 ( clk $end
$var wire 1 ) rst_n $end
$var reg 1 * led0 $end
$var reg 4 + counter [3:0] $end
$upscope $end
$upscope $end
$enddefinitions $end
#0
$dumpvars
0"
0#
x$
x*
bx +
x&
b1010 !
b1010 '
b0 %
0)
0(
$end
#5000
1"
1(
b0 +
0*
0$
#10000
0"
0(
#15000
1"
1(
#20000
0"
0(
#25000
1"
1(
#30000
0"
0(
1#
0&
1)
#35000
1"
1(
b1 +
#40000
0"
0(
#45000
1"
1(
b10 +
#50000
0"
0(
#55000
1"
1(
b11 +
#60000
0"
0(
#65000
1"
1(
b100 +
#70000
0"
0(
#75000
1"
1(
b101 +
#80000
0"
0(
#85000
1"
1(
b110 +
#90000
0"
0(
#95000
1"
1(
b111 +
#100000
0"
0(
#105000
1"
1(
b1000 +
#110000
0"
0(
#115000
1"
1(
b1001 +
#120000
0"
0(
#125000
1"
1(
b0 +
1*
1$
#130000
0"
0(
#135000
1"
1(
b1 %
1&
b1 +
#140000
0"
0(
#145000
1"
1(
b10 +
#150000
0"
0(
#155000
1"
1(
b11 +
#160000
0"
0(
#165000
1"
1(
b100 +
#170000
0"
0(
#175000
1"
1(
b101 +
#180000
0"
0(
#185000
1"
1(
b110 +
#190000
0"
0(
#195000
1"
1(
b111 +
#200000
0"
0(
#205000
1"
1(
b1000 +
#210000
0"
0(
#215000
1"
1(
b1001 +
#220000
0"
0(
#225000
1"
1(
b0 +
0*
0$
#230000
0"
0(
#235000
1"
1(
b10 %
0&
b1 +
#240000
0"
0(
#245000
1"
1(
b10 +
#250000
0"
0(
#255000
1"
1(
b11 +
#260000
0"
0(
#265000
1"
1(
b100 +
#270000
0"
0(
#275000
1"
1(
b101 +
#280000
0"
0(
#285000
1"
1(
b110 +
#290000
0"
0(
#295000
1"
1(
b111 +
#300000
0"
0(
#305000
1"
1(
b1000 +
#310000
0"
0(
#315000
1"
1(
b1001 +
#320000
0"
0(
#325000
1"
1(
b0 +
1*
1$
#330000
0"
0(
#335000
1"
1(
b11 %
1&
b1 +
#340000
0"
0(
#345000
1"
1(
b10 +
#350000
0"
0(
#355000
1"
1(
b11 +
#360000
0"
0(
#365000
1"
1(
b100 +
#370000
0"
0(
#375000
1"
1(
b101 +
#380000
0"
0(
#385000
1"
1(
b110 +
#390000
0"
0(
#395000
1"
1(
b111 +
#400000
0"
0(
#405000
1"
1(
b1000 +
#410000
0"
0(
#415000
1"
1(
b1001 +
#420000
0"
0(
#425000
1"
1(
b0 +
0*
0$
#430000
0"
0(
#435000
1"
1(
b100 %
0&
b1 +
#440000
0"
0(
#445000
1"
1(
b10 +
#450000
0"
0(
#455000
1"
1(
b11 +
#460000
0"
0(
#465000
1"
1(
b100 +
#470000
0"
0(
#475000
1"
1(
b101 +
#480000
0"
0(
#485000
1"
1(
b110 +
#490000
0"
0(
#495000
1"
1(
b111 +
#500000
0"
0(
#505000
1"
1(
b1000 +
#510000
0"
0(
#515000
1"
1(
b1001 +
#520000
0"
0(
#525000
1"
1(
b0 +
1*
1$
#530000
0"
0(
#535000
1"
1(
b101 %
1&
b1 +
#540000
0"
0(
#545000
1"
1(
b10 +
#550000
0"
0(
#555000
1"
1(
b11 +
#560000
0"
0(
#565000
1"
1(
b100 +
#570000
0"
0(
#575000
1"
1(
b101 +
#580000
0"
0(
#585000
1"
1(
b110 +
#590000
0"
0(
#595000
1"
1(
b111 +
#600000
0"
0(
#605000
1"
1(
b1000 +
#610000
0"
0(
#615000
1"
1(
b1001 +
#620000
0"
0(
#625000
1"
1(
b0 +
0*
0$
#630000
0"
0(
#635000
1"
1(
b110 %
0&
b1 +
#640000
0"
0(
#645000
1"
1(
b10 +
#650000
0"
0(
#655000
1"
1(
b11 +
#660000
0"
0(
#665000
1"
1(
b100 +
#670000
0"
0(
#675000
1"
1(
b101 +
#680000
0"
0(
#685000
1"
1(
b110 +
#690000
0"
0(
#695000
1"
1(
b111 +
#700000
0"
0(
#705000
1"
1(
b1000 +
#710000
0"
0(
#715000
1"
1(
b1001 +
#720000
0"
0(
#725000
1"
1(
b0 +
1*
1$
#730000
0"
0(
#735000
1"
1(
b111 %
1&
b1 +
#740000
0"
0(
#745000
1"
1(
b10 +
#750000
0"
0(
#755000
1"
1(
b11 +
#760000
0"
0(
#765000
1"
1(
b100 +
#770000
0"
0(
#775000
1"
1(
b101 +
#780000
0"
0(
#785000
1"
1(
b110 +
#790000
0"
0(
#795000
1"
1(
b111 +
#800000
0"
0(
#805000
1"
1(
b1000 +
#810000
0"
0(
#815000
1"
1(
b1001 +
